<?xml version="1.0" encoding="UTF-8"?>
<!DOCTYPE nitf SYSTEM "http://www.nitf.org/IPTC/NITF/3.3/specification/dtd/nitf-3-3.dtd">
<nitf change.date="June 10, 2005" change.time="19:30" version="-//IPTC//DTD NITF 3.3//EN">
  <head>
    <title>Cablevision's Chairman Named Richest Resident</title>
    <meta content="MB231149" name="slug"/>
    <meta content="1" name="publication_day_of_month"/>
    <meta content="10" name="publication_month"/>
    <meta content="2000" name="publication_year"/>
    <meta content="Sunday" name="publication_day_of_week"/>
    <meta content="Long Island Weekly Desk" name="dsk"/>
    <meta content="8" name="print_page_number"/>
    <meta content="14LI" name="print_section"/>
    <meta content="1" name="print_column"/>
    <meta content="New York and Region" name="online_sections"/>
    <docdata>
      <doc-id id-string="1235221"/>
      <doc.copyright holder="The New York Times" year="2000"/>
      <series series.name="IN BRIEF"/>
      <identified-content>
        <classifier class="indexing_service" type="descriptor">Millionaires and Billionaires</classifier>
        <classifier class="indexing_service" type="descriptor">Ratings and Rating Systems</classifier>
        <location class="indexing_service">Long Island (NY)</location>
        <org class="indexing_service">Forbes (Magazine)</org>
        <org class="indexing_service">Cablevision Inc</org>
        <person class="indexing_service">Dolen, Charles F</person>
        <person class="indexing_service">Strugatch, Warren</person>
        <classifier class="online_producer" type="taxonomic_classifier">Top/News/New York and Region</classifier>
        <classifier class="online_producer" type="taxonomic_classifier">Top/News/New York and Region/Long Island</classifier>
        <classifier class="online_producer" type="taxonomic_classifier">Top/News/U.S./U.S. States, Territories and Possessions/New York</classifier>
        <classifier class="online_producer" type="taxonomic_classifier">Top/Features/Travel/Guides/Destinations/North America/United States/New York/Long Island</classifier>
        <classifier class="online_producer" type="taxonomic_classifier">Top/Features/Travel/Guides/Destinations/North America</classifier>
        <classifier class="online_producer" type="taxonomic_classifier">Top/Features/Travel/Guides/Destinations/North America/United States</classifier>
        <classifier class="online_producer" type="taxonomic_classifier">Top/Features/Travel/Guides/Destinations/North America/United States/New York</classifier>
        <classifier class="online_producer" type="general_descriptor">Ratings and Rating Systems</classifier>
        <classifier class="online_producer" type="general_descriptor">Finances</classifier>
      </identified-content>
    </docdata>
    <pubdata date.publication="20001001T000000" ex-ref="http://query.nytimes.com/gst/fullpage.html?res=9F05E0DD143DF932A35753C1A9669C8B63" item-length="356" name="The New York Times" unit-of-measure="word"/>
  </head>
  <body>
    <body.head>
      <hedline>
        <hl1>Cablevision's Chairman Named Richest Resident</hl1>
      </hedline>
      <byline class="print_byline">Compiled by Warren Strugatch</byline>
      <byline class="normalized_byline">Strugatch, Warren</byline>
      <abstract>
        <p>Forbes magazine ranks Cablevision chairman Charles F Dolen, of Oyster Bay, with estimated worth of $3 billion, as Long Island's weathiest resident (S)</p>
      </abstract>
    </body.head>
    <body.content>
      <block class="lead_paragraph">
        <p>Charles F. Dolan, the chairman of Cablevision, is Long Island's wealthiest resident, Forbes magazine says. Mr. Dolan, 73, who lives in Oyster Bay, is worth an estimated $3 billion, ranking him 80th on the magazine's list of the 400 richest Americans, published in the Oct. 9 issue.</p>
        <p>Kenneth G. Langone, 65, of Roslyn Heights, a founder of Home Depot, was ranked 218th with $1.3 billion in estimated wealth.</p>
      </block>
      <block class="full_text">
        <p>Charles F. Dolan, the chairman of Cablevision, is Long Island's wealthiest resident, Forbes magazine says. Mr. Dolan, 73, who lives in Oyster Bay, is worth an estimated $3 billion, ranking him 80th on the magazine's list of the 400 richest Americans, published in the Oct. 9 issue.</p>
        <p>Kenneth G. Langone, 65, of Roslyn Heights, a founder of Home Depot, was ranked 218th with $1.3 billion in estimated wealth.</p>
        <p>Charles B. Wang, 56, the chairman of Computer Associates, who lives in Oyster Bay, ranked 330th, with an estimated wealth of $890 million.</p>
        <p>Park Electrochemical Sales and Earnings Rise</p>
        <p>The Park Electrochemical Corporation (NYSE: PKE) of Lake Success has reported that its sales increased to $129.9 million for the second quarter, up from $107.7 million in the same period last year. Sales for the first six months were $250 million, up from $212 million last year.</p>
        <p>Park reported second-quarter earnings of $11.7 million, up from $6 million in the second quarter last year. Earnings for the first six months were $20.5 million, compared with $11.7 million last year.</p>
        <p>Earnings per share also increased, to $1.10 for basic shares for the quarter, up from 58 cents last year. Earnings for diluted shares increased to 95 cents for the quarter, up from 53 cents last year.</p>
        <p>American Tissue Buys Global Tissue of Memphis</p>
        <p>American Tissue Inc., a closely held Hauppauge company, has acquired Global Tissue of Memphis. American Tissue, a toilet paper manufacturer, would not say what price it paid.</p>
        <p>The acquisition will increase the company's distribution and production capabilities and strengthen its position in the Southeast.</p>
        <p>In the past year, American Tissue has greatly expanded its operations through acquisitions, including the purchase the American Pad &amp; Paper Company in August.</p>
        <p>IN BRIEF E-mail: libiz@nytimes.com</p>
      </block>
    </body.content>
    <body.end>
      <tagline class="author_info">E-mail: libiz@nytimes.com</tagline>
    </body.end>
  </body>
</nitf>
