<?xml version="1.0" encoding="UTF-8"?>
<!DOCTYPE nitf SYSTEM "http://www.nitf.org/IPTC/NITF/3.3/specification/dtd/nitf-3-3.dtd">
<nitf change.date="June 10, 2005" change.time="19:30" version="-//IPTC//DTD NITF 3.3//EN">
  <head>
    <title>A Light Summer Reading List</title>
    <meta content="25WINE$01" name="slug"/>
    <meta content="25" name="publication_day_of_month"/>
    <meta content="6" name="publication_month"/>
    <meta content="2000" name="publication_year"/>
    <meta content="Sunday" name="publication_day_of_week"/>
    <meta content="The City Weekly Desk" name="dsk"/>
    <meta content="14" name="print_page_number"/>
    <meta content="14" name="print_section"/>
    <meta content="5" name="print_column"/>
    <meta content="New York and Region" name="online_sections"/>
    <docdata>
      <doc-id id-string="1210296"/>
      <doc.copyright holder="The New York Times" year="2000"/>
      <series series.name="WINE UNDER $20"/>
      <identified-content>
        <classifier class="indexing_service" type="descriptor">Alcoholic Beverages</classifier>
        <classifier class="indexing_service" type="descriptor">Reviews</classifier>
        <classifier class="indexing_service" type="descriptor">Wines</classifier>
        <person class="indexing_service">Goldberg, Howard G</person>
        <classifier class="online_producer" type="types_of_material">Review</classifier>
        <classifier class="online_producer" type="taxonomic_classifier">Top/News/New York and Region</classifier>
        <classifier class="online_producer" type="taxonomic_classifier">Top/News/New York and Region/The City</classifier>
        <classifier class="online_producer" type="taxonomic_classifier">Top/Features/Dining and Wine/Wine Reviews</classifier>
        <classifier class="online_producer" type="taxonomic_classifier">Top/Features/Travel/Guides/Activities and Interests/Food and Wine</classifier>
        <classifier class="online_producer" type="general_descriptor">Wines</classifier>
        <classifier class="online_producer" type="general_descriptor">Beverages</classifier>
        <classifier class="online_producer" type="general_descriptor">Alcoholic Beverages</classifier>
      </identified-content>
    </docdata>
    <pubdata date.publication="20000625T000000" ex-ref="http://query.nytimes.com/gst/fullpage.html?res=9F00E6DD1430F936A15755C0A9669C8B63" item-length="300" name="The New York Times" unit-of-measure="word"/>
  </head>
  <body>
    <body.head>
      <hedline>
        <hl1>A Light Summer Reading List</hl1>
      </hedline>
      <byline class="print_byline">By HOWARD G. GOLDBERG</byline>
      <byline class="normalized_byline">Goldberg, Howard G</byline>
      <abstract>
        <p>Howard Goldberg reviews summer white wines; photo (M)</p>
      </abstract>
    </body.head>
    <body.content>
      <block class="lead_paragraph">
        <p>To imagine how the critic Harold Bloom, a famously omnivorous reader, might feel in Barnes &amp; Noble, stroll into such Manhattan shops as Astor or Chelsea Wine Vault: So many wines, so little time. Even devotees of heavy fiction need light aperitif ''reads,'' like these summer whites.</p>
        <p>Burgundy The '98 Domaine de Champ Brule, a lovely, dry, fairly full-bodied Macon-Villages, $13.50, and the stylish, elegant '98 Pouilly-Fuisse $19, at Slope Cellars, 436 Seventh Avenue (15th Street), Park Slope, Brooklyn. (Both are Vincent Selections.)</p>
      </block>
      <block class="full_text">
        <p>To imagine how the critic Harold Bloom, a famously omnivorous reader, might feel in Barnes &amp; Noble, stroll into such Manhattan shops as Astor or Chelsea Wine Vault: So many wines, so little time. Even devotees of heavy fiction need light aperitif ''reads,'' like these summer whites.</p>
        <p>Burgundy The '98 Domaine de Champ Brule, a lovely, dry, fairly full-bodied Macon-Villages, $13.50, and the stylish, elegant '98 Pouilly-Fuisse $19, at Slope Cellars, 436 Seventh Avenue (15th Street), Park Slope, Brooklyn. (Both are Vincent Selections.)</p>
        <p>Loire Domaine Mardon '98 Quincy, vieilles vignes (old vines): This brisk wine, from vines dating back 80 years, delivers a tantalizing citric-herbal bouquet and splendid herbal finish. Let it linger on your palate. Chelsea Wine Vault, 75 Ninth Avenue (15th Street), Manhattan, asks $14. (Distributed by Jeroboam Wines, owned by Daniel Johnnes, Montrachet's wine director.)</p>
        <p>Spain Osborne Coquinero fino amontillado, an unusual sherry -- an aged fino -- of bracing dryness, with hints of almond. This pale, understated entry-level aperitif, which doubles your appetite, is $12 at 67 Wine, 179 Columbus Avenue (68th Street), Manhattan.</p>
        <p>Fino stales quickly. Insist on a recent consignment, keep the wine iced, finish in 10 days. Think serrano ham or prosciutto, olives, nuts and Manchego cheese. The convivial English critic Hugh Johnson hits the bull's-eye: a glass of fino before or after gazpacho.</p>
        <p>Chile The '98 Laura Hartwig chardonnay, a pretty, appley, to-the-point refresher from Santa Laura, a small producer that has attracted favorable notices: $13 at Brite-Buy, 11 Avenue of the Americas (Walker Street), Manhattan. (From Jeroboam.)</p>
        <p>HOWARD G. GOLDBERG</p>
        <p>WINE UNDER $20</p>
      </block>
    </body.content>
  </body>
</nitf>
